hexa/__init__.py
hexa/main.py
hexa_sdk-0.1.1.dist-info/METADATA
hexa_sdk-0.1.1.dist-info/WHEEL
hexa_sdk-0.1.1.dist-info/RECORD
