Metadata-Version: 2.3
Name: hexa-sdk
Version: 0.1.1
Summary: A short description of your project
Author: Felix
Author-email: lampkole@gmail.com
Requires-Python: >=3.9
Classifier: Programming Language :: Python :: 3
Classifier: Programming Language :: Python :: 3.9
Classifier: Programming Language :: Python :: 3.10
Classifier: Programming Language :: Python :: 3.11
Classifier: Programming Language :: Python :: 3.12
Classifier: Programming Language :: Python :: 3.13
Requires-Dist: requests (>=2.31.0,<3.0.0)
